Workbook

Sheet in
A1: pais_de_origem | B1: razao_social | C1: cnpj | D1: logradouro | E1: cidade | F1: uf | G1: cep | H1: e_mail | I1: cotm | J1: adesao_ao_decreto_1563_95 | K1: vigencia_mês | L1: vigencia_dia | M1: vigencia_ano | N1: vigencia_data | O1: Coluna1
A2: BRASIL | B2: Agiliza Transportes E Logística Eireli | C2: 7953712000174 | D2: ROD. BR 277, KM 720, S/N, SALA 17 - ANEXO AO POSTO GASPARIN | F2: PR | G2: 85862000 | H2: leandro@agilizatransportes.com.br | I2: 0224-0107 | J2: Sim | K2: 11 | L2: 9 | M2: 2031 | N2: =DATE(M2,K2,L2) -> 48161 | O2: 00:00:00.000000
A3: BRASIL | B3: Alerta Transportes E Armazéns Gerais Ltda - Epp | C3: 10496449000146 | D3: Rodovia BR 277, km 720, nº 10.595 - Parque Três Fronteiras | F3: PR | G3: 85859688 | H3: delmar@transp-amizade.com.br | I3: 0900-0418 | J3: Sim | K3: 4 | L3: 5 | M3: 2028 | N3: =DATE(M3,K3,L3) -> 46848 | O3: 00:00:00.000000
A4: BRASIL | B4: Áquila Transporte De Cargas Ltda | C4: 3608196000190 | D4: STRC TRECHO 04 CONJ. C LOTE 09 - ZONA INDUSTRIAL | F4: DF | G4: 71225543 | H4: marcelo@aquilaexpress.com.br | I4: 0419-1110 | J4: Não | K4: 6 | L4: 29 | M4: 2032 | N4: =DATE(M4,K4,L4) -> 48394 | O4: 00:00:00.000000
A5: BRASIL | B5: Brazil Relocation & Services Ltda | C5: 4314143000129 | D5: RUA 13, QD. 49, LOTE 32 E 33 - PARQUE ESPLANADA II | F5: GO | G5: 72878036 | H5: adm1@brazilrelocatin.com | I5: 0412-0910 | J5: Sim | K5: 11 | L5: 12 | M5: 2030 | N5: =DATE(M5,K5,L5) -> 47799 | O5: 00:00:00.000000
A6: BRASIL | B6: Brucal Implementos Rodoviários Ltda | C6: 76188846000169 | D6: Rod. dos Minérios, km23,5, nº14552 - Areias | F6: PR | G6: 83514000 | H6: fernando@brucalimplementos.com.br | I6: 0659-1214 | J6: Sim | K6: 12 | L6: 30 | M6: 2024 | N6: =DATE(M6,K6,L6) -> 45656 | O6: 00:00:00.000000
A7: BRASIL | B7: Bun Log Serviços Logisticos Ltda | C7: 35957917000163 | D7: RUA ROQUE MEDALDO FRIAS, Nº 1341, GAÇPÃO 05, SALA 01, TÉRREO - RECREIO CAMPESTRE JOIA | F7: SP | G7: 13347035 | H7: rmendes@bentonit.com.br | I7: 1171-0621 | J7: Não | K7: 6 | L7: 22 | M7: 2031 | N7: =DATE(M7,K7,L7) -> 48021 | O7: 00:00:00.000000
A8: BRASIL | B8: Ciagram Portos E Navegação Da Amazônia Ltda | C8: 2900972000168 | D8: R I QUADRA E - LOTE 02 - SETOR INDUSTRIAL | F8: AM | G8: 69800000 | H8: logistica@masutti.com.br | I8: 1269-0622 | J8: Não | K8: 6 | L8: 22 | M8: 2032 | N8: =DATE(M8,K8,L8) -> 48387 | O8: 00:00:00.000000
A9: BRASIL | B9: Eckert & Ziegler Brasil Logistica Ltda | C9: 21423605000165 | D9: RUA MIGUEL NELSON BECHARA, 480 - TERREO - SALA 01 - BAIRRO - JARDIM PEREIRA LEITE | F9: SP | G9: 2712130 | H9: clarice.almeida@ezag.com | I9: 1085-0620 | J9: Sim | K9: 6 | L9: 12 | M9: 2030 | N9: =DATE(M9,K9,L9) -> 47646 | O9: 00:00:00.000000
A10: BRASIL | B10: Gencon Logistica Transportes E Armazéns Gerais Ltda | C10: 7263198000145 | D10: Av. Fernando Cerqueira César Coimbra - 830 - Bloco 02 - Parque Industrial Cacique - Londrina | F10: PR | G10: 86072110 | H10: italo@compager.com.br | I10: 0579-0913 | J10: Sim | K10: 9 | L10: 10 | M10: 2023 | N10: =DATE(M10,K10,L10) -> 45179 | O10: 00:00:00.000000
A11: PARAGUAI | B11: Grupo G3 Sociedade Anonima | C11: 53412 | D11: RUTA 6, CRUCE 14 DE MAYO, SANTA RITA | H11: maxypytterh@hotmail.com | I11: 0534-1212 | J11: Sim | K11: 12 | L11: 10 | M11: 2022 | N11: =DATE(M11,K11,L11) -> 44905 | O11: 00:00:00.000000
A12: BRASIL | B12: Jbs S.A. | C12: 2916265000160 | D12: AV. MARGINAL DIREITA DO TIETE, 500 - ANDAR 3 BLOCO I | F12: SP | G12: 5118100 | H12: cassio.sanches@jbs.com.br | I12: 1023-1019 | J12: Não | K12: 10 | L12: 1 | M12: 2029 | N12: =DATE(M12,K12,L12) -> 47392 | O12: 00:00:00.000000
A13: BRASIL | B13: Jr Pereira Transportes Ltda | C13: 51024961000177 | D13: EST DO CAIXA PARA, 120, LEVILÂNDIA, ANANINDEUA | F13: PA | G13: 67015520 | H13: didimopereira@hotmail.com | I13: 1407-0224 | J13: Não | K13: 2 | L13: 8 | M13: 2034 | N13: =DATE(M13,K13,L13) -> 48983 | O13: 00:00:00.000000
A14: BRASIL | B14: Katoen Natie Do Brasil Ltda | C14: 40924102000118 | D14: Avenida Viena, nº 419 - Distrito Industrial | F14: SP | G14: 13146055 | H14: regulatorios@katoennatie.com.br | I14: 0214-1106 | J14: Sim | K14: 10 | L14: 19 | M14: 2026 | N14: =DATE(M14,K14,L14) -> 46314 | O14: 00:00:00.000000
A15: BRASIL | B15: Leramarc Transportes E Logística Ltda | C15: 31000248000186 | D15: Rua Antonio Soster, 287 - Jardim Regina | F15: SP | G15: 13348897 | H15: rafael@leramarc.com.br | I15: 0987-0519 | J15: Não | K15: 5 | L15: 9 | M15: 2029 | N15: =DATE(M15,K15,L15) -> 47247 | O15: 00:00:00.000000
A16: BRASIL | B16: Logjato Transportes E Logistica Eireli | C16: 24514316000160 | D16: Segunda Avenida Bloco 1385A, Loja 1 | F16: DF | G16: 71710555 | H16: logjatobsb@gmail.com | I16: 0794-1016 | J16: Não | K16: 10 | L16: 5 | M16: 2026 | N16: =DATE(M16,K16,L16) -> 46300 | O16: 00:00:00.000000
A17: BRASIL | B17: Logmed Rio Armazenagem E Transporte Ltda | C17: 22044907000195 | D17: RUA FRANCISCO DE S E MELO, 01590, ARMAZEN Nº 103 GALPÃO 03 | F17: RJ | G17: 21010900 | H17: juridico@logmed.net | I17: 1028-1019 | J17: Não | K17: 10 | L17: 10 | M17: 2029 | N17: =DATE(M17,K17,L17) -> 47401 | O17: 00:00:00.000000
A18: DINAMARCA | B18: Maersk Line A/S | C18: 21386088000100 | D18: Esplanaden 50, 1098 | H18: gustavo.candido@maersk.com | I18: 0667-0315 | J18: Não | K18: 3 | L18: 25 | M18: 2025 | N18: =DATE(M18,K18,L18) -> 45741 | O18: 00:00:00.000000
A19: BRASIL | B19: Marca Sul Mudanças E Transportes Ltda | C19: 3126110000192 | D19: SCIA Quadra 08, conj.08, lote 13 | F19: DF | G19: 71250710 | H19: bsb@granero.com.br | I19: 0804-1116 | J19: Não | K19: 11 | L19: 11 | M19: 2026 | N19: =DATE(M19,K19,L19) -> 46337 | O19: 00:00:00.000000
A20: BRASIL | B20: Medylog Logística E Distribuição Ltda | C20: 11958200000178 | D20: RUA 24 (Polo de Modas) - LOTE 05 - QE 40 | F20: DF | G20: 71070524 | H20: MEDYLOGADM@GMAIL.COM | I20: 1311-1222 | J20: Não | K20: 12 | L20: 1 | M20: 2032 | N20: =DATE(M20,K20,L20) -> 48549 | O20: 00:00:00.000000
A21: BRASIL | B21: Megatranz Transportes Ltda | C21: 3061794000191 | D21: Av. Major Sylvio de Magalhães Padilha, 5200 - Bl. E - 5º andar - Conjunto 507 | F21: SP | G21: 5693000 | H21: MEGATRANZ@megatranz.com | I21: 0081-0605 | J21: Sim | K21: 6 | L21: 8 | M21: 2027 | N21: =DATE(M21,K21,L21) -> 46546 | O21: 00:00:00.000000
A22: BRASIL | B22: Mel Logística E Desembaraço Aduaneiro Eireli - Me | C22: 23756206000141 | D22: RUA WALTER MACHADO, 841 QUADRA D LOTE 05 ( CX POSTAL 187) | F22: GO | G22: 75375000 | H22: ricardo@mellogistica.com.br | I22: 0824-0217 | J22: Não | K22: 2 | L22: 10 | M22: 2027 | N22: =DATE(M22,K22,L22) -> 46428 | O22: 00:00:00.000000
A23: BRASIL | B23: Noble Brasil S.A | C23: 6315338000119 | D23: Avenida Rebouças nº 3.970, 22º andar - Condomínio Eldorado Business Tower | F23: SP | G23: 5402920 | H23: julianamedeiros@thisisnoble.com | I23: 0493-0512 | J23: Não | K23: 5 | L23: 25 | M23: 2022 | N23: =DATE(M23,K23,L23) -> 44706 | O23: 00:00:00.000000
A24: BRASIL | B24: Northin Logística E Servicos De Navegação Ltda | C24: 41248280000139 | D24: EST. ESTADUAL DO ANEL VIARIO S/N - GALPÃO 02 - SALA 02 - AREA RURAL | F24: RO | G24: 76914899 | H24: igorchaves98@hotmail.com | I24: 1394-1223 | J24: Não | K24: 12 | L24: 20 | M24: 2033 | N24: =DATE(M24,K24,L24) -> 48933 | O24: 00:00:00.000000
A25: BRASIL | B25: Nova Solução Logística & Transporte Ltda | C25: 33805990000194 | D25: Estrada Angela Trevisan Ciciliato, Nº 200, Galpão 01, Modulo 01 - Jardim Oliveira Camargo | F25: SP | G25: 13340730 | H25: diretoria@novasolucaolog.com | I25: 1440-0824 | J25: Não | K25: 8 | L25: 23 | M25: 2034 | N25: =DATE(M25,K25,L25) -> 49179 | O25: 00:00:00.000000
A26: BRASIL | B26: Pacheco Logística Ltda | C26: 14144376000184 | D26: RUA DONA MARGARIDA, Nº 903 | F26: RS | G26: 90240611 | H26: contabilidade@grupodarcypacheco.com.br | I26: 0568-0713 | J26: Sim | K26: 7 | L26: 22 | M26: 2023 | N26: =DATE(M26,K26,L26) -> 45129 | O26: 00:00:00.000000
A27: BRASIL | B27: Paradiso Giovanella Transportes Ltda | C27: 68979111000125 | D27: Rua José Simeão Rodrigues Agostinho, n º 502 - sala 03 - Bairro Água Espraiadas | F27: SP | G27: 6833300 | H27: adm@transgiovanella.com.br | I27: 0072-0505 | J27: Sim | K27: 6 | L27: 7 | M27: 2015 | N27: =DATE(M27,K27,L27) -> 42162 | O27: 00:00:00.000000
A28: BRASIL | B28: Rm Melo Transforporte Rodoviario E Aereo De Cargas Ltda | C28: 12323649000122 | D28: QUADRA 3, CONJUNTO B, LOTE 6, SETOR DE INDUSTRIAS BERNARDO SAYAO | F28: DF | G28: 71736302 | H28: RODRIGO@ALFAEXPRESSDF.COM.BR | I28: 1446-0924 | J28: Não | K28: 9 | L28: 30 | M28: 2034 | N28: =DATE(M28,K28,L28) -> 49217 | O28: 00:00:00.000000
A29: BRASIL | B29: Rodorei Transportes Ltda | C29: 68577659000149 | D29: Rua Salete nº 200 Cj. 81/82 | F29: SP | G29: 2016001 | H29: reinaldo@rodorei.com.br | I29: 0535-0113 | J29: Não | K29: 1 | L29: 3 | M29: 2023 | N29: =DATE(M29,K29,L29) -> 44929 | O29: 00:00:00.000000
A30: BRASIL | B30: Sec Figueiredo Ltda - Epp | C30: 43448117000145 | D30: RUA ESTELA Nº 515 - BLOCO H - 3 ANDAR - CJ 31 | F30: SP | G30: 4011002 | H30: eduardo@secfigueiredo.com.br | I30: 0524-1012 | J30: Não | K30: 10 | L30: 8 | M30: 2022 | N30: =DATE(M30,K30,L30) -> 44842 | O30: 00:00:00.000000
... A43: BRASIL | B43: Yes Brazil Express Cargas Ltda | C43: 2006743000102 | D43: RUA JOSE FERNANDES TEIXEIRA (ZUZA), 1091 - VILA ROSA | F43: SP | G43: 6317270 | H43: contab.luz@terra.com.br | I43: 1037-1119 | J43: Não | K43: 11 | L43: 12 | M43: 2029 | N43: =DATE(M43,K43,L43) -> 47434 | O43: 00:00:00.000000
A44: ALEMANHA | B44: HAPAG-LLOYD AG | C44: 8219447000168 | D44: Ballindamm, 25 - 20095 Hamburg - Germany | H44: intimacoes@hlag.com | I44: 0696-0715 | J44: Não | K44: 6 | L44: 23 | M44: 2035 | N44: =DATE(M44,K44,L44) -> 49483 | O44: 18:27:11.901169
A45: BRASIL | B45: Greca Transportes De Cargas S.A. | C45: 242640000108 | D45: Avenida das Araucarias nº 5126 - Chapada | F45: PR | G45: 83707000 | H45: andrea@grecaasfaltos.com.br | I45: 0510-0812 | J45: Sim | K45: 6 | L45: 22 | M45: 2032 | N45: =DATE(M45,K45,L45) -> 48387 | O45: 00:00:00.000000
A46: CHILE | B46: CSAV AUSTRAL SPA | C46: 71015 | D46: 14 Norte 976, Piso 12, Viña del Mar | H46: intimacoes@hlag.com | I46: 0710-0915 | J46: Não | K46: 7 | L46: 30 | M46: 2035 | N46: =DATE(M46,K46,L46) -> 49520 | O46: 18:41:05.863034
A47: CHILE | B47: CSAV AUSTRAL SPA | C47: 71015 | D47: 14 Norte 976, Piso 12, Viña del Mar | H47: luanabrancacio@hotmail.com | I47: 0710-0915 | J47: Não | K47: 7 | L47: 30 | M47: 2035 | N47: =DATE(M47,K47,L47) -> 49520 | O47: 18:41:05.863034
A48: BRASIL | B48: Tangara Logistica E Transportes Eireli - Epp | C48: 12900343000191 | D48: AV. ADINEI EMIDIO DE ALMEIDA, Nº 1893 - BAIRRO INDUSTRIAL | E48: Cacoal | F48: RO | G48: 76960970 | H48: fernando@piarara.com.br | I48: 1221-0122 | J48: Não | K48: 1 | L48: 25 | M48: 2032 | N48: =DATE(M48,K48,L48) -> 48238 | O48: 00:00:00.000000
A49: BRASIL | B49: Piarara Transportes Ltda | C49: 1746769000116 | D49: Rod. BR 364, KM 232, Lote 08-B, Gleba 08, Pavilhão A | E49: Cacoal | F49: RO | G49: 76960970 | H49: contabilidadetransportes@piarara.com.br | I49: 0348-1009 | J49: Sim | K49: 7 | L49: 11 | M49: 2029 | N49: =DATE(M49,K49,L49) -> 47310 | O49: 00:00:00.000000
A50: BRASIL | B50: P & F Transportes Eireli | C50: 13564310000180 | D50: EST DO BELMONT Nº 9349 KM 04 - BAIRRO NACIONAL | E50: Porto Velho | F50: RO | G50: 76801870 | H50: gustavoskiadv@gmail.com | I50: 0441-0711 | J50: Não | K50: 10 | L50: 4 | M50: 2031 | N50: =DATE(M50,K50,L50) -> 48125 | O50: 00:00:00.000000
A51: BRASIL | B51: Noroeste Transporte E Serviços Ltda | C51: 84552827000106 | D51: Rua João Pedro da Rocha, 2740 | E51: Porto Velho | F51: RO | G51: 76820888 | H51: dionemrios@uol.com.br | I51: 0462-1111 | J51: Não | K51: 11 | L51: 8 | M51: 2021 | N51: =DATE(M51,K51,L51) -> 44508 | O51: 00:00:00.000000
A52: BRASIL | B52: Bdx Logística Ltda | C52: 17589247000198 | D52: ESTRADA DO TERMINAL Nº 400 BAIRRO: PANAIR | E52: Porto Velho | F52: RO | G52: 76801370 | H52: bdxlogistica@gmail.com | I52: 1371-0923 | J52: Sim | K52: 9 | L52: 1 | M52: 2033 | N52: =DATE(M52,K52,L52) -> 48823 | O52: 00:00:00.000000
A53: BRASIL | B53: OCEAN RIVER DO BRASIL LOGISTICA INTEGRADA LTDA | C53: 62768709000199 | D53: AV LAURO SODRÉ, 1865 | E53: Porto Velho | F53: RO | G53: 76801501 | H53: FISCAL@OCEANRIVER.COM.BR | I53: 1521-1125 | J53: Não | K53: 11 | L53: 10 | M53: 2035 | N53: =DATE(M53,K53,L53) -> 49623 | O53: 17:13:11.761184
A54: BRASIL | B54: Raro Transportes E Com. Imp. E Exp. Ltda | C54: 23589040000116 | D54: EST. BR 317 KM 02 Nº 1500 - FUNDOS SALA B - ZONA RURAL | E54: Brasiléia | F54: AC | G54: 69932000 | H54: RARODISTRIBUIDORA@UOL.COM.BR | I54: 1047-0120 | J54: Não | K54: 1 | L54: 27 | M54: 2030 | N54: =DATE(M54,K54,L54) -> 47510 | O54: 00:00:00.000000
A55: BRASIL | B55: Logsul Investy Ltda Me | C55: 10541783000174 | D55: Rua Parintins, nº 44 - Conjunto Universitário III | E55: Rio Branco | F55: AC | G55: 69917748 | H55: jonilson.marinho@hotmail.com | I55: 0927-0918 | J55: Não | K55: 9 | L55: 3 | M55: 2028 | N55: =DATE(M55,K55,L55) -> 46999 | O55: 00:00:00.000000
A56: BRASIL | B56: Comércio E Navegação Prates Ltda | C56: 4443961000121 | D56: MARGEM DIREITA DO RIO NEGRO ESTRADA DO BRITO, CACAU PIRERA, N 06 | E56: Iranduba | F56: AM | G56: 69421000 | H56: financeiro@navegacaoprates.com.br | I56: 1355-0623 | J56: Não | K56: 6 | L56: 15 | M56: 2033 | N56: =DATE(M56,K56,L56) -> 48745 | O56: 00:00:00.000000
A57: BRASIL | B57: F C Transporte E Turismo Eireli | C57: 84084383000113 | D57: RUA CAROLINA FERNANDES Nº 1045 - SÃO JOSÉ | E57: Manacapuru | F57: AM | G57: 69400797 | H57: hpgadelha@gmail.com | I57: 1281-0822 | J57: Não | K57: 8 | L57: 22 | M57: 2032 | N57: =DATE(M57,K57,L57) -> 48448 | O57: 00:00:00.000000
A58: BRASIL | B58: Rio Solimões Navegação E Transportes Ltda | C58: 608456000139 | D58: Travessa Aniceto Barroso, nº 282, andar 01, sala 03, Bairro Terra Preta, | E58: Manacapuru | F58: AM | G58: 69401278 | H58: riosolimoesnav@gmail.com | I58: 1457-1224 | J58: Não | K58: 12 | L58: 9 | M58: 2034 | N58: =DATE(M58,K58,L58) -> 49287 | O58: 00:00:00.000000
A59: BRASIL | B59: Pimentel Turismo E Transportes Ltda | C59: 7612370000129 | D59: TRAVESSA ANICETO BARROSO, Nº 282, 1º ANDAR, SALA 04 - TERRA PRETA | E59: Manacapuru | F59: AM | G59: 69401278 | H59: pimentelturismoltda@gmail.com | I59: 1423-0624 | J59: Não | K59: 6 | L59: 3 | M59: 2034 | N59: =DATE(M59,K59,L59) -> 49098 | O59: 00:00:00.000000
... A276: BRASIL | B276: Rapidão 7 Logística E Transporte S/A | C276: 10970887000102 | D276: Av. Engenheiro Antônio de Góes, nº 60, sala 1.605 - Pina | E276: Recife | F276: PE | G276: 51110000 | H276: gadotti@rapidaocometa.com.br | I276: 0106-0805 | J276: Não | K276: 8 | L276: 18 | M276: 2015 | N276: =DATE(M276,K276,L276) -> 42234 | O276: 00:00:00.000000
A277: BRASIL | B277: Lsa Transportes Especializados Ltda | C277: 1537428000130 | D277: Rua Rio Araguaia nº 206 A - Afogados | E277: Recife | F277: PE | G277: 50750050 | I277: 0529-1112 | J277: Sim | K277: 11 | L277: 7 | M277: 2022 | N277: =DATE(M277,K277,L277) -> 44872 | O277: 00:00:00.000000
A278: BRASIL | B278: Mota Logistica E Transporte Ltda | C278: 21765067000197 | D278: AV MAL. JUAREZ TÁVORA, 440 - SL9 - BOA VIAGEM | E278: Recife | F278: PE | G278: 51130115 | H278: joao.mota@ativacargo.com | I278: 1215-1221 | J278: Não | K278: 12 | L278: 27 | M278: 2031 | N278: =DATE(M278,K278,L278) -> 48209 | O278: 00:00:00.000000
A279: BRASIL | B279: Ampla Logística Ltda | C279: 29219812000104 | D279: Rua Jornalista Edson Regis, 456, Galpão 04 - Ibura | E279: Recife | F279: PE | G279: 51220000 | H279: MILCA@AMPLALOGISTICA.COM.BR | I279: 1445-0924 | J279: Não | K279: 9 | L279: 19 | M279: 2034 | N279: =DATE(M279,K279,L279) -> 49206 | O279: 00:00:00.000000
A280: BRASIL | B280: Agemar Transportes E Empreendimentos Ltda | C280: 8745465000183 | D280: AVENIDA RIO BRANCO Nº 243 - 2º ANDAR | E280: Recife | F280: PE | G280: 50030310 | H280: AGEMAR@AGEMAR.COM.BR | I280: 1376-0923 | J280: Não | K280: 9 | L280: 15 | M280: 2033 | N280: =DATE(M280,K280,L280) -> 48837 | O280: 00:00:00.000000
A281: BRASIL | B281: Atlantis Logística Importadora E Exportadora Ltda | C281: 7775361000159 | D281: Rua Antônio Lumack do Monte, nº 128, Sala 406 - Boa Viagem | E281: Recife | F281: PE | G281: 51020350 | H281: logistica@atlantislog.com.br | I281: 0627-0714 | J281: Não | K281: 7 | L281: 16 | M281: 2024 | N281: =DATE(M281,K281,L281) -> 45489 | O281: 00:00:00.000000
A282: BRASIL | B282: Emmanuel A. Da S. Ramalho Transportes - Me | C282: 24718688000108 | D282: Rua Tenente Portela, nº 165 - Ibura | E282: Recife | F282: PE | G282: 51190740 | H282: emmanuelramalho@sitlog.com.br | I282: 0958-1218 | J282: Não | K282: 12 | L282: 10 | M282: 2028 | N282: =DATE(M282,K282,L282) -> 47097 | O282: 00:00:00.000000
A283: BRASIL | B283: Itaguary Agenciamento E Transporte De Cargas Ltda | C283: 69907541000102 | D283: Rua Pintor Lula Cardoso Ayres, 3196 | E283: Recife | F283: PE | G283: 51200250 | H283: neemias.franca@itaguary.com.br | I283: 0984-0519 | J283: Não | K283: 5 | L283: 9 | M283: 2029 | N283: =DATE(M283,K283,L283) -> 47247 | O283: 00:00:00.000000
A284: BRASIL | B284: ENGEMAN MANUTENCAO DE EQUIPAMENTOS COM E INDUSTRIA LTDA | C284: 8769549000157 | D284: RUA PADRE CARAPUCEIRO | E284: Recife | F284: PE | G284: 51020280 | H284: junior.beltrao@engeman.net | I284: 1522-1125 | J284: Sim | K284: 11 | L284: 18 | M284: 2035 | N284: =DATE(M284,K284,L284) -> 49631 | O284: 19:01:14.203794
A285: BRASIL | B285: Last Mile Logística Ltda | C285: 35364161000149 | D285: Rua Dom Bosco, 537, Sala 13 | E285: Aracaju | F285: SE | G285: 49052140 | H285: RONTNETO@GMAIL.COM | I285: 1469-0225 | J285: Não | K285: 2 | L285: 12 | M285: 2035 | N285: =DATE(M285,K285,L285) -> 49352 | O285: 18:31:56.069560
A286: BRASIL | B286: Real Distribuidora Ltda | C286: 4633195000168 | D286: Avenida Presidente Tancredo Neves, nº 4913 Jabotiana Galpão 31 e 32 | E286: Aracaju | F286: SE | G286: 49095000 | H286: viviane@realdistribuidora.com | I286: 0550-0313 | J286: Não | K286: 3 | L286: 8 | M286: 2023 | N286: =DATE(M286,K286,L286) -> 44993 | O286: 00:00:00.000000
A287: BRASIL | B287: Empresa De Transportes E Logística Paraná Ltda | C287: 16066888000103 | D287: Via Parafuso, Km 13 e 14 - Bairro Industrial Urbano | E287: Camaçari | F287: BA | G287: 42800970 | H287: qualidade@etp-transparana.com.br | I287: 0863-1017 | J287: Não | K287: 10 | L287: 5 | M287: 2027 | N287: =DATE(M287,K287,L287) -> 46665 | O287: 00:00:00.000000
A288: BRASIL | B288: RELIMPP SERVIÇOS INDUSTRIAIS LTDA | C288: 9070341000108 | D288: RUA JOSE FLORIANO LAGO, | E288: Catu | F288: BA | G288: 48110000 | H288: comercial@relimpp.com.br | I288: 1527-0226 | J288: Não | K288: 2 | L288: 20 | M288: 2036 | N288: =DATE(M288,K288,L288) -> 49725 | O288: 18:21:08.791543
A289: BRASIL | B289: Nacional Transportes E Atacado De Alimentos Ltda | C289: 7377407000181 | D289: Praça Vereador José Adry, nº 26 , sala 01 - Centro | E289: Itajuípe | F289: BA | G289: 45600201 | H289: nacional.adm1@gmail.com | I289: 0934-0918 | J289: Não | K289: 9 | L289: 12 | M289: 2028 | N289: =DATE(M289,K289,L289) -> 47008 | O289: 00:00:00.000000
... A794: BRASIL | B794: CARPO LOGISTICS LTDA | C794: 7353607000102 | D794: Praça Barão do Rio Branco, nº 14 | E794: Santos | F794: SP | G794: 11010040 | H794: ADM@CARPOLOG.COM.BR | I794: 0089-0605 | J794: Não | K794: 7 | L794: 27 | M794: 2036 | N794: =DATE(M794,K794,L794) -> 49883 | O794: 13:58:31.507451
A795: BRASIL | B795: Caf Transportes Internacionais Ltda | C795: 27096000181 | D795: Av. Senador Feijó, 14 - 6º andar - Conj. 62 | E795: Santos | F795: SP | G795: 11015500 | I795: 0157-1205 | J795: Não | K795: 12 | L795: 28 | M795: 2015 | N795: =DATE(M795,K795,L795) -> 42366 | O795: 00:00:00.000000
A796: BRASIL | B796: Ccis Brasil Ltda | C796: 52247381000101 | D796: Alameda Armênio Mendes, nº 66 - Andar 21, Conj. 2108 - Aparecida | E796: Santos | F796: SP | G796: 11035260 | H796: bma.legal@cma-cgm.com | I796: 1419-0424 | J796: Sim | K796: 4 | L796: 22 | M796: 2034 | N796: =DATE(M796,K796,L796) -> 49056 | O796: 00:00:00.000000
A797: BRASIL | B797: Custom Brasil Ltda | C797: 4309775000102 | D797: AV. SÃO FRANCISCO Nº 65 - 9º ANDAR - CENTRO | E797: Santos | F797: SP | G797: 11013201 | H797: CUSTOMBRASIL@CUSTOMBRASIL.COM | I797: 0566-0713 | J797: Não | K797: 7 | L797: 17 | M797: 2023 | N797: =DATE(M797,K797,L797) -> 45124 | O797: 00:00:00.000000
A798: BRASIL | B798: Contrail Logísitica S.A. | C798: 10140658000152 | D798: PRAÇA DOS EXPEDICONÁRIOS, Nº 19, CJ. 61, GONZAGA | E798: Santos | F798: SP | G798: 11065922 | H798: juridico@contrail.com.br | I798: 0468-1211 | J798: Não | K798: 12 | L798: 22 | M798: 2021 | N798: =DATE(M798,K798,L798) -> 44552 | O798: 00:00:00.000000
A799: BRASIL | B799: Conquest - Logística E Consultoria Aduaneira Ltda. | C799: 96407705000105 | D799: Rua Brás Cubas, nº 9, 5º andar, salas 11 A 14 | E799: Santos | F799: SP | G799: 11013161 | H799: comercial@conquestilogistica.com.br | I799: 0129-1005 | J799: Sim | K799: 10 | L799: 13 | M799: 2015 | N799: =DATE(M799,K799,L799) -> 42290 | O799: 00:00:00.000000
A800: BRASIL | B800: Costa Brasil Cabotagem Ltda | C800: 7649313000114 | D800: PC Antônio Telles, nº 12 sala 13 - Centro | E800: Santos | F800: SP | G800: 11013020 | H800: alessandro.camargo@cabotagem.com.br | I800: 0257-0907 | J800: Não | K800: 9 | L800: 28 | M800: 2017 | N800: =DATE(M800,K800,L800) -> 43006 | O800: 00:00:00.000000
A801: BRASIL | B801: Costa Brasil Cabotagem Ltda | C801: 7649313000114 | D801: PC Antônio Telles, nº 12 sala 13 - Centro | E801: Santos | F801: SP | G801: 11013020 | H801: alessandro.camargo@cabotagem.com.br | I801: 0875-1217 | J801: Não | K801: 12 | L801: 15 | M801: 2027 | N801: =DATE(M801,K801,L801) -> 46736 | O801: 00:00:00.000000
A802: BRASIL | B802: Antonio Alexandre Moreira Galante | C802: 9629581000108 | D802: RUA BRAZ CUBAS, Nº 3, 3º ANDAR, SALA 19 - CENTRO | E802: Santos | F802: SP | G802: 11013918 | H802: alexandremgalante@gmail.com | I802: 0881-0118 | J802: Não | K802: 1 | L802: 29 | M802: 2028 | N802: =DATE(M802,K802,L802) -> 46781 | O802: 00:00:00.000000
A803: BRASIL | B803: Agilink Transporte Rodoviário Ltda | C803: 24960415000175 | D803: Avenida Senador Feijó, 686, Sala 1527 B, 15º andar - Vila Mathias | E803: Santos | F803: SP | G803: 11015504 | H803: marcelo.benvenuti@takelog.com.br | I803: 1300-0922 | J803: Não | K803: 9 | L803: 30 | M803: 2032 | N803: =DATE(M803,K803,L803) -> 48487 | O803: 00:00:00.000000
A804: BRASIL | B804: Açologis Multimodal Ltda | C804: 40272996000109 | D804: Rua General Câmara, 20, sala 43 - Centro | E804: Santos | F804: SP | G804: 11010123 | H804: mara.masiero@acologis.com.br | I804: 1152-0321 | J804: Não | K804: 3 | L804: 30 | M804: 2031 | N804: =DATE(M804,K804,L804) -> 47937 | O804: 00:00:00.000000
A805: BRASIL | B805: Atlântico Norte Logística Ltda | C805: 31527624000195 | D805: Praça dos Andradas, 12 - 7º andar - Centro | E805: Santos | F805: SP | G805: 11010904 | H805: juridico@fcnaccounting.com | I805: 0985-0519 | J805: Sim | K805: 5 | L805: 9 | M805: 2029 | N805: =DATE(M805,K805,L805) -> 47247 | O805: 00:00:00.000000
A806: BRASIL | B806: As-Road Transportes Ltda | C806: 31574231000132 | D806: Rua General Câmara, 05 - sala 404 - Centro | E806: Santos | F806: SP | G806: 11010902 | H806: nathalia.marcal@br-asgroup.com | I806: 0976-0419 | J806: Não | K806: 4 | L806: 1 | M806: 2029 | N806: =DATE(M806,K806,L806) -> 47209 | O806: 00:00:00.000000
A807: BRASIL | B807: Asf Logística Integrada Ltda | C807: 5596162000158 | D807: RUA VISCONDE DO RIO BRANCO, 02 SALA 91 D - CENTRO | E807: Santos | F807: SP | G807: 11013030 | H807: martinsassessoria@uol.com.br | I807: 1375-0923 | J807: Não | K807: 9 | L807: 12 | M807: 2033 | N807: =DATE(M807,K807,L807) -> 48834 | O807: 00:00:00.000000
... A830: BRASIL | B830: Fks Logsitics Ltda | C830: 17353801000133 | D830: RUA JOSÉ VERSOLATO, Nº 111, BLOCO A, SALA 102 - CENTRO | E830: São Bernardo do Campo | F830: SP | G830: 9750730 | H830: franciely.azzolini@fkslogisticis.com.br | I830: 1042-1119 | J830: Não | K830: 11 | L830: 26 | M830: 2029 | N830: =DATE(M830,K830,L830) -> 47448 | O830: 00:00:00.000000
A831: BRASIL | B831: Fita Azul Transportes E Logística Ltda | C831: 22507975000143 | D831: RUA TIETE, Nº 189 - RUDGE RAMOS | E831: São Bernardo do Campo | F831: SP | G831: 9615000 | I831: 1433-0724 | J831: Não | K831: 7 | L831: 18 | M831: 2034 | N831: =DATE(M831,K831,L831) -> 49143 | O831: 00:00:00.000000
A832: BRASIL | B832: Tegma Gestão Logística S.A. | C832: 2351144000118 | D832: AV. NICOLA DEMARCHI, 2000 - BAIRRO DEMARCHI | E832: São Bernardo do Campo | F832: SP | G832: 9820655 | H832: ect_ged@tegma.com.br | I832: 0389-0610 | J832: Sim | K832: 8 | L832: 3 | M832: 2030 | N832: =DATE(M832,K832,L832) -> 47698 | O832: 00:00:00.000000
A833: BRASIL | B833: Tl Transportes Expressos De Cargas Ltda | C833: 2767766000121 | D833: Rua Oswaldo Cruz, nº 50 - Vila Jordanopolis | E833: São Bernardo do Campo | F833: SP | G833: 9892250 | H833: kleber.legalizacao@paulicon.com.br | I833: 0916-0818 | J833: Não | K833: 8 | L833: 13 | M833: 2028 | N833: =DATE(M833,K833,L833) -> 46978 | O833: 00:00:00.000000
A834: BRASIL | B834: Tomé Engenharia E Transporte Ltda. | C834: 44384832000100 | D834: Avenida José Odorizzi, nº 900 - Bairro Assunção | E834: São Bernardo do Campo | F834: SP | G834: 9810900 | H834: sidney@tome.com.br | I834: 0085-0605 | J834: Sim | K834: 6 | L834: 22 | M834: 2015 | N834: =DATE(M834,K834,L834) -> 42177 | O834: 00:00:00.000000
A835: BRASIL | B835: Tomé Equipamentos E Transportes Ltda | C835: 44384832000124 | D835: Av. José Odorizzi, 900 - Bairro Assunção | E835: São Bernardo do Campo | F835: SP | G835: 9810900 | H835: sidnei@tome.com.br | I835: 1296-0922 | J835: Não | K835: 9 | L835: 29 | M835: 2032 | N835: =DATE(M835,K835,L835) -> 48486 | O835: 00:00:00.000000
A836: BRASIL | B836: Sada Transportes E Armazenagens Ltda | C836: 19199348000188 | D836: Estrada dos Alvarengas, nº 4018 - Assunção | E836: São Bernardo do Campo | F836: SP | G836: 9850550 | H836: NOELMA.GOMES@BRAZUL.COM.BR | I836: 0107-0805 | J836: Sim | K836: 11 | L836: 6 | M836: 2034 | N836: =DATE(M836,K836,L836) -> 49254 | O836: 00:00:00.000000
A837: BRASIL | B837: Sada Transportes E Armazenagens Ltda | C837: 19199348000188 | D837: Estrada dos Alvarengas, nº 4018 - Assunção | E837: São Bernardo do Campo | F837: SP | G837: 9850550 | H837: CAMILA.SILVA@BRAZUL.COM.BR | I837: 0107-0805 | J837: Sim | K837: 11 | L837: 6 | M837: 2034 | N837: =DATE(M837,K837,L837) -> 49254 | O837: 00:00:00.000000
A838: BRASIL | B838: Transportes Furlong Do Brasil S/A | C838: 67599878000166 | D838: Av. Maria Servidei Demarchi, 1826 - Bairro Demarchi | E838: São Bernardo do Campo | F838: SP | G838: 9820000 | H838: anapaula.petruske@furlong.com.br | I838: 0077-0605 | J838: Sim | K838: 8 | L838: 23 | M838: 2029 | N838: =DATE(M838,K838,L838) -> 47353 | O838: 00:00:00.000000
A839: BRASIL | B839: Piquetur Log Logistica E Transporte Ltda | C839: 4045101000130 | D839: Avenida Lauro Gomes, nº 1.200 - Rudger Ramos | E839: São Bernardo do Campo | F839: SP | G839: 9635010 | H839: financeiro1@piquetur.com.br | I839: 0617-0514 | J839: Não | K839: 5 | L839: 22 | M839: 2024 | N839: =DATE(M839,K839,L839) -> 45434 | O839: 00:00:00.000000
A840: BRASIL | B840: Lachmann Terminais Ltda | C840: 21613553000190 | D840: Estrada Assumpta Sabatini Rossi, nº 920 - Batistini | E840: São Bernardo do Campo | F840: SP | G840: 9842000 | H840: juridico@lachmann.com.br | I840: 0896-0418 | J840: Não | K840: 4 | L840: 4 | M840: 2028 | N840: =DATE(M840,K840,L840) -> 46847 | O840: 00:00:00.000000
A841: BRASIL | B841: Shipmasters International Freight Agenciamento De Frete Ltda | C841: 22677138000162 | D841: AL CAULIM 115 CONJ 307 E 308 EDIF TORRE GATE | E841: São Caetano do Sul | F841: SP | G841: 9531195 | H841: marcio.oliveira@ship-masters.com | I841: 1427-0624 | J841: Não | K841: 6 | L841: 19 | M841: 2034 | N841: =DATE(M841,K841,L841) -> 49114 | O841: 00:00:00.000000
A842: BRASIL | B842: Temp Transporte E Distribuição Ltda | C842: 66764457000180 | D842: RUA MAJOR CARLOS DEL PRETE, 724 - CENTRO | E842: São Caetano do Sul | F842: SP | G842: 9530000 | H842: carlos.buran@templog.net | I842: 0344-0909 | J842: Não | K842: 12 | L842: 24 | M842: 2031 | N842: =DATE(M842,K842,L842) -> 48206 | O842: 00:00:00.000000
A843: BRASIL | B843: Birktrans Logística E Despachos Ltda. | C843: 9296130000198 | D843: Rua Pernambuco, nº 425, 1º andar, Conj. 14 - Centro | E843: São Caetano do Sul | F843: SP | G843: 9521140 | H843: felipe.sao@birktrans.com.br | I843: 0334-0509 | J843: Não | K843: 5 | L843: 23 | M843: 2032 | N843: =DATE(M843,K843,L843) -> 48357 | O843: 00:00:00.000000
... A1244: BRASIL | B1244: Transportes Macuim Ltda | C1244: 13091403000135 | D1244: RUA GERONIMO FRANCISCHINI Nº 713 - NOVA MILANO | E1244: Farroupilha | F1244: RS | G1244: 95182000 | H1244: FINANCEIRO@MBLOGTRANSPORTES.COM.BR | I1244: 1294-0922 | J1244: Não | K1244: 9 | L1244: 20 | M1244: 2032 | N1244: =DATE(M1244,K1244,L1244) -> 48477 | O1244: 00:00:00.000000
A1245: BRASIL | B1245: Transportadora Plimor Ltda. | C1245: 88085485000104 | D1245: Rod. RS122, S/N, Km 61 - Bairro Industrial | E1245: Farroupilha | F1245: RS | G1245: 95180000 | I1245: 0192-0606 | J1245: Não | K1245: 6 | L1245: 26 | M1245: 2016 | N1245: =DATE(M1245,K1245,L1245) -> 42547 | O1245: 00:00:00.000000
A1246: BRASIL | B1246: Vinhedos Transportes Ltda | C1246: 93561108000134 | D1246: RUA CLEMENTE PEDRO DALCIN, 375 - BAIRRO - TAMANDARE | E1246: Garibaldi | F1246: RS | G1246: 95720000 | H1246: pauloguerra@vinhedostransportesa.com.br | I1246: 1104-0820 | J1246: Não | K1246: 8 | L1246: 13 | M1246: 2030 | N1246: =DATE(M1246,K1246,L1246) -> 47708 | O1246: 00:00:00.000000
A1247: BRASIL | B1247: ATRHOL AGÊNCIA E TRANSPORTES HORIZONTINA LTDA | C1247: 6208105000117 | D1247: Rua das Indústrias, nº 245 | E1247: Horizontina | F1247: RS | G1247: 98920000 | H1247: jorge@atrhol.com.br | I1247: 1475-0225 | J1247: Sim | K1247: 2 | L1247: 25 | M1247: 2035 | N1247: =DATE(M1247,K1247,L1247) -> 49365 | O1247: 17:28:42.796007
A1248: BRASIL | B1248: Cassio Rafael Cansi & Cia Ltda | C1248: 7902228000116 | D1248: RUA DOS IMIGRANDES Nº 688 - CENTRO | E1248: Horizontina | F1248: RS | G1248: 98920000 | H1248: cassio@flechaazul.com.br | I1248: 1063-0320 | J1248: Não | K1248: 3 | L1248: 18 | M1248: 2030 | N1248: =DATE(M1248,K1248,L1248) -> 47560 | O1248: 00:00:00.000000
A1249: BRASIL | B1249: Canaro Transportes Ltda | C1249: 22938787000170 | D1249: RODOVIA BR 386, KM 342 - Nº 5827 - SALA 02 - OLARIAS | E1249: Lajeado | F1249: RS | G1249: 95910160 | H1249: lajeado@canarotransportes.com.br | I1249: 1373-0923 | J1249: Não | K1249: 9 | L1249: 11 | M1249: 2033 | N1249: =DATE(M1249,K1249,L1249) -> 48833 | O1249: 00:00:00.000000
A1250: BRASIL | B1250: Mtl Transporte Rodoviário De Cargas Ltda | C1250: 11274148000130 | D1250: Rua Rudolfo Behne, 166, prédio 2 - Centro | E1250: Lindolfo Collor | F1250: RS | G1250: 93940000 | H1250: alvaro@gminuano.com.br | I1250: 1096-0720 | J1250: Não | K1250: 7 | L1250: 30 | M1250: 2030 | N1250: =DATE(M1250,K1250,L1250) -> 47694 | O1250: 00:00:00.000000
A1251: BRASIL | B1251: Deposul Transporte E Logística Ltda | C1251: 23815200000106 | D1251: ESTRADA MONTENEGRO POLO RS 124, SN, GALPÃO DEPOSUL KM 16 SALA 06 | E1251: Montenegro | F1251: RS | G1251: 95529899 | H1251: gg@ngcontabil.com.br | I1251: 1386-1123 | J1251: Não | K1251: 11 | L1251: 6 | M1251: 2033 | N1251: =DATE(M1251,K1251,L1251) -> 48889 | O1251: 00:00:00.000000
A1252: BRASIL | B1252: Top Global Assessoria Aduaneira Ltda | C1252: 9031864000145 | D1252: RUA BARÃO DE COTEGIPE Nº 44 - PRIMAVERA | E1252: Novo Hamburgo | F1252: RS | G1252: 93344260 | H1252: diego@topglobalprovider.com.br | I1252: 0796-1016 | J1252: Não | K1252: 10 | L1252: 18 | M1252: 2026 | N1252: =DATE(M1252,K1252,L1252) -> 46313 | O1252: 00:00:00.000000
A1253: BRASIL | B1253: SK TRANSPORTE E LOGÍSTICA LTDA | C1253: 39283025000185 | D1253: Rua Vinte e Cinco de Julho, nº 1151, Loja 2 | E1253: Novo Hamburgo | F1253: RS | G1253: 93310251 | H1253: luisfernando@azulcargors.com.br | I1253: 1495-0525 | J1253: Não | K1253: 5 | L1253: 12 | M1253: 2035 | N1253: =DATE(M1253,K1253,L1253) -> 49441 | O1253: 21:21:57.957711
A1254: BRASIL | B1254: MCN TRANSPORTE E LOGISTICA INTERNACIONAL LTDA | C1254: 7620879000466 | D1254: AV DAS INDUSTRIAS N.º 469 - SALA 202 E 203 | E1254: Porto Alegre | F1254: RS | G1254: 90200290 | H1254: qualidade@macenor.com | I1254: 1512-0825 | J1254: Sim | K1254: 8 | L1254: 12 | M1254: 2035 | N1254: =DATE(M1254,K1254,L1254) -> 49533 | O1254: 17:03:13.997551
...

Sheet Gráficos
A1: uf | B1: Quantidade Empresas Habilitadas Multimodal | D1: pais_de_origem | E1: Quantidade de Empresas
A2: PR | B2: =COUNTIF(in!F:F,Gráficos!A2) -> 74
A3: DF | B3: =COUNTIF(in!F:F,Gráficos!A3) -> 64 | D3: PARAGUAI | E3: =COUNTIF(in!A:A,Gráficos!D3) -> 1
A4: GO | B4: =COUNTIF(in!F:F,Gráficos!A4) -> 25 | D4: DINAMARCA | E4: =COUNTIF(in!A:A,Gráficos!D4) -> 2
A5: SP | B5: =COUNTIF(in!F:F,Gráficos!A5) -> 569 | D5: ALEMANHA | E5: =COUNTIF(in!A:A,Gráficos!D5) -> 1
A6: AM | B6: =COUNTIF(in!F:F,Gráficos!A6) -> 98 | D6: CHILE | E6: =COUNTIF(in!A:A,Gráficos!D6) -> 2
B7: =COUNTIF(in!F:F,Gráficos!A7) -> 0 | D7: SUÍÇA | E7: =COUNTIF(in!A:A,Gráficos!D7) -> 1
A8: PA | B8: =COUNTIF(in!F:F,Gráficos!A8) -> 62
A9: RJ | B9: =COUNTIF(in!F:F,Gráficos!A9) -> 110
A10: RO | B10: =COUNTIF(in!F:F,Gráficos!A10) -> 7 | D10: Quantas empresas tem origem em outro país exceto o Brasil?
A11: RS | B11: =COUNTIF(in!F:F,Gráficos!A11) -> 82
A12: SC | B12: =COUNTIF(in!F:F,Gráficos!A12) -> 74
A13: MT | B13: =COUNTIF(in!F:F,Gráficos!A13) -> 12
A14: AC | B14: =COUNTIF(in!F:F,Gráficos!A14) -> 2
A15: RR | B15: =COUNTIF(in!F:F,Gráficos!A15) -> 1
A16: AP | B16: =COUNTIF(in!F:F,Gráficos!A16) -> 1
A17: TO | B17: =COUNTIF(in!F:F,Gráficos!A17) -> 2
A18: MA | B18: =COUNTIF(in!F:F,Gráficos!A18) -> 8
A19: PI | B19: =COUNTIF(in!F:F,Gráficos!A19) -> 2
A20: CE | B20: =COUNTIF(in!F:F,Gráficos!A20) -> 29
A21: RN | B21: =COUNTIF(in!F:F,Gráficos!A21) -> 6
A22: PB | B22: =COUNTIF(in!F:F,Gráficos!A22) -> 2
... A28: MS | B28: =COUNTIF(in!F:F,Gráficos!A28) -> 2
B29: =COUNTIF(in!F:F,Gráficos!A29) -> 0
A31: Qual estado tem mais empresas habilitadas multimodal?
